ML_Translator
